README.md
setup.py
prysm/__init__.py
prysm/coral.py
prysm/icecore.py
prysm/lake.py
prysm/speleo.py
prysm/tree.py
prysm_api.egg-info/PKG-INFO
prysm_api.egg-info/SOURCES.txt
prysm_api.egg-info/dependency_links.txt
prysm_api.egg-info/not-zip-safe
prysm_api.egg-info/requires.txt
prysm_api.egg-info/top_level.txt