Metadata-Version: 2.1
Name: prysm-api
Version: 0.5.1
Summary: The API for PRoxY System Modeling (PRYSM)
Home-page: https://github.com/fzhu2e/prysm-api
Author: Sylvia Dee, Amir Allam, and Feng Zhu
License: MIT license
Keywords: prysm-api
Platform: UNKNOWN
Classifier: License :: OSI Approved :: MIT License
Classifier: Natural Language :: English
Classifier: Programming Language :: Python :: 3
Classifier: Programming Language :: Python :: 3.6
